{
  "_comment": "Maps every Ohio State department code to a key in author-byline.json. All departments currently map to 'general' per explicit confirmation that this author's real credentials span all academic subjects, not just philosophy/humanities.",
  "mappings": {
    "ohio-state.AEDECON": "general",
    "ohio-state.ANTHROP": "general",
    "ohio-state.ART": "general",
    "ohio-state.ARTEDUC": "general",
    "ohio-state.ARTSSCI": "general",
    "ohio-state.BUSADM": "general",
    "ohio-state.BUSMHR": "general",
    "ohio-state.CLAS": "general",
    "ohio-state.COMM": "general",
    "ohio-state.COMPSTD": "general",
    "ohio-state.CSE": "general",
    "ohio-state.DESIGN": "general",
    "ohio-state.EARTHSC": "general",
    "ohio-state.ECON": "general",
    "ohio-state.EHE": "general",
    "ohio-state.ENGLISH": "general",
    "ohio-state.ENGR": "general",
    "ohio-state.ENR": "general",
    "ohio-state.ESEPSY": "general",
    "ohio-state.ESPHE": "general",
    "ohio-state.FDSCTE": "general",
    "ohio-state.FRENCH": "general",
    "ohio-state.GENED": "general",
    "ohio-state.GEOG": "general",
    "ohio-state.GERMAN": "general",
    "ohio-state.HDFS": "general",
    "ohio-state.HTHRHSC": "general",
    "ohio-state.KNSFHP": "general",
    "ohio-state.KNSISM": "general",
    "ohio-state.KOREAN": "general",
    "ohio-state.LAW": "general",
    "ohio-state.MATH": "general",
    "ohio-state.MEDCOLL": "general",
    "ohio-state.MICRBIO": "general",
    "ohio-state.MOLGEN": "general",
    "ohio-state.MUSIC": "general",
    "ohio-state.PHILOS": "general",
    "ohio-state.PHR": "general",
    "ohio-state.PLNTPTH": "general",
    "ohio-state.POLITSC": "general",
    "ohio-state.PORTGSE": "general",
    "ohio-state.PSYCH": "general",
    "ohio-state.PUBAFRS": "general",
    "ohio-state.PUBHEHS": "general",
    "ohio-state.PUBHEPI": "general",
    "ohio-state.PUBHLTH": "general",
    "ohio-state.RADSCI": "general",
    "ohio-state.SLAVIC": "general",
    "ohio-state.SOCIOL": "general",
    "ohio-state.SOCWORK": "general",
    "ohio-state.SPANISH": "general",
    "ohio-state.STAT": "general",
    "ohio-state.THEATRE": "general",
    "ohio-state.TLED": "general",
    "ohio-state.TLIELP": "general",
    "ohio-state.WGSST": "general",
    "fordham.philosophy": "philosophy-humanities"
  }
}
